aimm/__init__.py
aimm/client/__init__.py
aimm/client/repl.py
aimm/common.py
aimm/json_schema_repo.json
aimm/plugins/__init__.py
aimm/plugins/common.py
aimm/plugins/decorators.py
aimm/plugins/execute.py
aimm/server/__init__.py
aimm/server/__main__.py
aimm/server/backend/__init__.py
aimm/server/backend/dummy.py
aimm/server/backend/event.py
aimm/server/backend/sqlite.py
aimm/server/common.py
aimm/server/control/__init__.py
aimm/server/control/event.py
aimm/server/control/repl.py
aimm/server/engine.py
aimm/server/main.py
aimm/server/mprocess.py
aimm/server/runners.py
aimm-1.2.dev1.dist-info/LICENSE
aimm-1.2.dev1.dist-info/METADATA
aimm-1.2.dev1.dist-info/WHEEL
aimm-1.2.dev1.dist-info/entry_points.txt
aimm-1.2.dev1.dist-info/RECORD
