Metadata-Version: 2.3
Name: aimm
Version: 1.2.dev1
Summary: Artificial intelligence model manager
License: Apache
Author: zlatsic
Author-email: zlatan.sicanica@gmail.com
Requires-Python: >=3.10,<4.0
Classifier: Development Status :: 1 - Planning
Classifier: Intended Audience :: Developers
Classifier: License :: OSI Approved :: Apache Software License
Classifier: License :: Other/Proprietary License
Classifier: Natural Language :: English
Classifier: Operating System :: Unix
Classifier: Programming Language :: Python :: 3
Classifier: Programming Language :: Python :: 3.10
Classifier: Programming Language :: Python :: 3.11
Classifier: Programming Language :: Python :: 3.12
Classifier: Programming Language :: Python :: 3.13
Classifier: Topic :: Software Development :: Libraries
Classifier: Topic :: Utilities
Requires-Dist: appdirs (>=1.4.4,<2.0.0)
Requires-Dist: hat-aio (>=0.7,<0.8)
Requires-Dist: hat-event (>=0.9,<0.10)
Requires-Dist: hat-json (>=0.6,<0.7)
Requires-Dist: hat-juggler (>=0.7,<0.8)
Requires-Dist: hat-monitor (>=0.8,<0.9)
Requires-Dist: jsonschema-rs (>=0.30,<0.31)
Requires-Dist: psutil (>=7.0,<8.0)
Requires-Dist: tenacity (>=9.1,<10.0)
